{
  "timeline": [
    {
      "quarter": "Q1 2023",
      "title": "Windows Support Release",
      "status": "done"
    },
    {
      "quarter": "Q1 2024",
      "title": "Scoring System Implementation",
      "status": "done"
    },
    {
      "quarter": "Q4 2024",
      "title": "Linux Support",
      "status": "done"
    },
    {
      "quarter": "Q4 2024",
      "title": "New EDR Additions - Windows",
      "status": "done"
    },
    {
      "quarter": "Q1 2025",
      "title": "New EDR Additions - Windows/Linux",
      "status": "current"
    },
    {
      "quarter": "Q4 2025",
      "title": "MacOS Support",
      "status": "planned"
    }
  ],
  "inProgress": [
    {
      "title": "Pull Request Reviews",
      "description": "Processing community contributions and EDR updates.",
      "status": "Ongoing"
    }
  ],
  "planned": [
    {
      "title": "New EDR Additions",
      "description": "Integration of additional EDR solutions including:",
      "items": ["Cylance","BitDefender"],
      "status": "Planned for Q4 2024"
    }
  ],
  "backlog": [
    {
        "title": "Wazuh EDR",
        "description": "Integration with Wazuh EDR and telemetry analysis.",
        "status": "Planning - Q4 2024"
      },
    {
      "title": "MacOS Support",
      "description": "Expanding platform support to include MacOS systems.",
      "status": "Not Started"
    }
  ]
}